config2class/__init__.py
config2class/__main__.py
config2class/_core/__init__.py
config2class/_core/code_abstraction.py
config2class/_core/constructor.py
config2class/_core/entrypoint.py
config2class/_service/__init__.py
config2class/_service/api_funcs.py
config2class/_service/backend.py
config2class/_service/config.py
config2class/_service/pid_coordination.py
config2class/_utils/__init__.py
config2class/_utils/deconstruction.py
config2class/_utils/dict_operations.py
config2class/_utils/filesystem.py
config2class/_utils/omega_conf.py
config2class/_utils/parser.py
config2class/_utils/replacement.py
config2class/_utils/token_operations.py
config2class/api/__init__.py
config2class/api/base.py
config2class/api/construct.py
config2class/api/hydra.py
config2class-0.3.1.dist-info/LICENSE
config2class-0.3.1.dist-info/METADATA
config2class-0.3.1.dist-info/WHEEL
config2class-0.3.1.dist-info/entry_points.txt
config2class-0.3.1.dist-info/RECORD
