Metadata-Version: 2.1
Name: config2class
Version: 0.3.1
Summary: Config2Code simplifies configuration management by automatically generating Python dataclasses from YAML or JSON files. This tool enhances code readability, maintainability, and type safety, saving you time and effort.
Home-page: https://github.com/RobinU434/Config2Class
License: MIT
Keywords: autocomplete,structured-config,code-generation,configuration
Author: Robin Uhrich
Author-email: robin.uhrich@gmx.de
Requires-Python: >=3.10,<4.0
Classifier: License :: OSI Approved :: MIT License
Classifier: Programming Language :: Python :: 3
Classifier: Programming Language :: Python :: 3.10
Classifier: Programming Language :: Python :: 3.11
Classifier: Programming Language :: Python :: 3.12
Classifier: Programming Language :: Python :: 3.13
Requires-Dist: hydra-core (>=1.3.2,<2.0.0)
Requires-Dist: omegaconf (>=2.3.0,<3.0.0)
Requires-Dist: pyaml (>=23.0.0,<24.0.0)
Requires-Dist: toml (>=0.10.2,<0.11.0)
Requires-Dist: watchdog (>=6.0.0,<7.0.0)
Project-URL: Repository, https://github.com/RobinU434/Config2Class
